vibekit_cli-0.3.3.dist-info/licenses/LICENSE
vk/__init__.py
vk/cli.py
vk/py.typed
vk/auth/__init__.py
vk/auth/client.py
vk/auth/config.py
vk/auth/tokens.py
vk/client/__init__.py
vk/client/api.py
vk/client/exceptions.py
vk/generator/__init__.py
vk/generator/claude_md.py
vk/generator/codebase_docs.py
vk/generator/detector.py
vk/generator/lsp_config.py
vk/generator/plan_md.py
vk/generator/precommit_config.py
vk/generator/project_md.py
vk/sync/__init__.py
vk/sync/client.py
vk/sync/models.py
vk/sync/realtime.py
vk/sync/state_manager.py
vibekit_cli-0.3.3.dist-info/METADATA
vibekit_cli-0.3.3.dist-info/WHEEL
vibekit_cli-0.3.3.dist-info/entry_points.txt
vibekit_cli-0.3.3.dist-info/top_level.txt
vibekit_cli-0.3.3.dist-info/RECORD
