Metadata-Version: 2.4
Name: vibekit-cli
Version: 0.3.3
Summary: VibeKit CLI - Configure AI coding workflows in SaaS, execute locally
Author: VibeKit Contributors
License: MIT
Project-URL: Homepage, https://vkcli.com
Project-URL: Documentation, https://vkcli.com/docs
Project-URL: Repository, https://github.com/AgeofIA/vibe-kit
Project-URL: Issues, https://github.com/AgeofIA/vibe-kit/issues
Keywords: vibekit,vkcli,claude-code,ai-coding,sprint-management,saas,cli
Classifier: Development Status :: 4 - Beta
Classifier: Intended Audience :: Developers
Classifier: License :: OSI Approved :: MIT License
Classifier: Programming Language :: Python :: 3
Classifier: Programming Language :: Python :: 3.9
Classifier: Programming Language :: Python :: 3.10
Classifier: Programming Language :: Python :: 3.11
Classifier: Programming Language :: Python :: 3.12
Requires-Python: >=3.9
License-File: LICENSE
Requires-Dist: typer>=0.9.0
Requires-Dist: rich>=13.0.0
Requires-Dist: httpx>=0.27.0
Requires-Dist: pyyaml>=6.0
Requires-Dist: keyring>=25.0.0
Requires-Dist: pydantic>=2.0.0
Requires-Dist: PyJWT>=2.8.0
Requires-Dist: resend>=2.19.0
Provides-Extra: dev
Requires-Dist: pytest>=7.0.0; extra == "dev"
Requires-Dist: pytest-cov>=4.0.0; extra == "dev"
Requires-Dist: black>=23.0.0; extra == "dev"
Requires-Dist: ruff>=0.1.0; extra == "dev"
Requires-Dist: mypy>=1.0.0; extra == "dev"
Dynamic: license-file
